forgit/__init__.py
forgit/__version__
forgit/main.py
forgit/utils/__init__.py
forgit/utils/github_tools.py
forgit-0.0.1.dist-info/DESCRIPTION.rst
forgit-0.0.1.dist-info/METADATA
forgit-0.0.1.dist-info/RECORD
forgit-0.0.1.dist-info/WHEEL
forgit-0.0.1.dist-info/entry_points.txt
forgit-0.0.1.dist-info/metadata.json
forgit-0.0.1.dist-info/top_level.txt
