Metadata-Version: 2.0
Name: forgit
Version: 0.0.1
Summary: Tools for git and github
Home-page: https://github.com/draperjames/forgit
Author: James Draper
Author-email: james.draper@duke.edu
License: MIT
Keywords: Git
Platform: UNKNOWN
Classifier: Development Status :: 3 - Alpha
Classifier: Intended Audience :: Developers
Classifier: Topic :: Software Development :: Build Tools
Classifier: License :: OSI Approved :: MIT License
Classifier: Programming Language :: Python :: 3.4
Classifier: Programming Language :: Python :: 3.5
Classifier: Programming Language :: Python :: 3.6
